pybuses/__init__.py
pybuses/command_bus.py
pybuses/event_bus.py
pybuses/foundation.py
pybuses/types.py
tests/__init__.py
tests/conftest.py
tests/test_command_bus.py
tests/test_event_bus.py
pybuses-1.1.0.dist-info/LICENSE
pybuses-1.1.0.dist-info/METADATA
pybuses-1.1.0.dist-info/WHEEL
pybuses-1.1.0.dist-info/top_level.txt
pybuses-1.1.0.dist-info/RECORD
