Metadata-Version: 2.1
Name: pybuses
Version: 1.1.0
Summary: Pythonic Command & Event buses
Home-page: https://github.com/Enforcer/pybuses
Author: Sebastian Buczyński
Author-email: nnplaya@gmail.com
License: UNKNOWN
Platform: UNKNOWN
Classifier: Programming Language :: Python :: 3
Classifier: License :: OSI Approved :: MIT License
Classifier: Operating System :: OS Independent
